dipin/__init__.py
dipin/container.py
dipin/interface.py
dipin/py.typed
dipin/resolver.py
dipin/util.py
dipin-0.0.3.dist-info/METADATA
dipin-0.0.3.dist-info/WHEEL
dipin-0.0.3.dist-info/licenses/LICENSE.md
dipin-0.0.3.dist-info/RECORD
