Metadata-Version: 2.3
Name: dipin
Version: 0.0.3
Summary: Dependency injection helper for FastAPI
Project-URL: Homepage, https://github.com/rmasters/dipin
Project-URL: Issues, https://github.com/rmasters/dipin/issues
Author-email: Ross Masters <ross@rossmasters.com>
License-File: LICENSE.md
Classifier: Development Status :: 2 - Pre-Alpha
Classifier: Framework :: FastAPI
Classifier: Intended Audience :: Developers
Classifier: License :: OSI Approved :: MIT License
Classifier: Operating System :: OS Independent
Classifier: Programming Language :: Python :: 3
Classifier: Programming Language :: Python :: 3 :: Only
Classifier: Programming Language :: Python :: 3.12
Classifier: Programming Language :: Python :: 3.13
Classifier: Topic :: Internet :: WWW/HTTP
Classifier: Topic :: Internet :: WWW/HTTP :: WSGI :: Middleware
Classifier: Typing :: Typed
Requires-Python: >=3.12
Requires-Dist: asyncer>=0.0.7
Requires-Dist: fastapi>=0.111.0
